{
  "__inputs": [
    {
      "name": "DS_PROMETHEUS",
      "label": "Prometheus PGbouncer",
      "description": "",
      "type": "datasource",
      "pluginId": "prometheus",
      "pluginName": "Prometheus"
    }
  ],
  "__requires": [
    {
      "type": "grafana",
      "id": "grafana",
      "name": "Grafana",
      "version": "5.0.4"
    },
    {
      "type": "panel",
      "id": "graph",
      "name": "Graph",
      "version": "5.0.0"
    },
    {
      "type": "datasource",
      "id": "prometheus",
      "name": "Prometheus",
      "version": "5.0.0"
    },
    {
      "type": "panel",
      "id": "singlestat",
      "name": "Singlestat",
      "version": "5.0.0"
    }
  ],
  "annotations": {
    "list": [
      {
        "builtIn": 1,
        "datasource": "-- Grafana --",
        "enable": true,
        "hide": true,
        "iconColor": "rgba(0, 211, 255, 1)",
        "name": "Annotations & Alerts",
        "type": "dashboard"
      }
    ]
  },
  "editable": true,
  "gnetId": 9760,
  "graphTooltip": 0,
  "id": null,
  "iteration": 1549459380138,
  "links": [],
  "panels": [
    {
      "cacheTimeout": null,
      "colorBackground": false,
      "colorValue": true,
      "colors": [
        "#299c46",
        "rgba(237, 129, 40, 0.89)",
        "#d44a3a"
      ],
      "datasource": "$datasource",
      "format": "none",
      "gauge": {
        "maxValue": 30000,
        "minValue": 0,
        "show": true,
        "thresholdLabels": false,
        "thresholdMarkers": true
      },
      "gridPos": {
        "h": 6,
        "w": 5,
        "x": 0,
        "y": 0
      },
      "id": 6,
      "interval": null,
      "links": [],
      "mappingType": 1,
      "mappingTypes": [
        {
          "name": "value to text",
          "value": 1
        },
        {
          "name": "range to text",
          "value": 2
        }
      ],
      "maxDataPoints": 100,
      "minSpan": null,
      "nullPointMode": "connected",
      "nullText": null,
      "postfix": "",
      "postfixFontSize": "50%",
      "prefix": "",
      "prefixFontSize": "50%",
      "rangeMaps": [
        {
          "from": "null",
          "text": "N/A",
          "to": "null"
        }
      ],
      "repeat": null,
      "repeatDirection": "h",
      "sparkline": {
        "fillColor": "rgba(31, 118, 189, 0.18)",
        "full": false,
        "lineColor": "rgb(31, 120, 193)",
        "show": true
      },
      "tableColumn": "__name__",
      "targets": [
        {
          "expr": "sum (pgbouncer_pools_client_active_connections{database=~\"$db\",hostname=~\"$hostname\"})",
          "format": "time_series",
          "intervalFactor": 1,
          "refId": "A"
        }
      ],
      "thresholds": "15000,25000,30000",
      "title": "Client active connections $db",
      "transparent": true,
      "type": "singlestat",
      "valueFontSize": "80%",
      "valueMaps": [
        {
          "op": "=",
          "text": "N/A",
          "value": "null"
        }
      ],
      "valueName": "current"
    },
    {
      "cacheTimeout": null,
      "colorBackground": false,
      "colorValue": false,
      "colors": [
        "#299c46",
        "rgba(237, 129, 40, 0.89)",
        "#d44a3a"
      ],
      "datasource": "$datasource",
      "format": "short",
      "gauge": {
        "maxValue": 300000,
        "minValue": 0,
        "show": true,
        "thresholdLabels": false,
        "thresholdMarkers": true
      },
      "gridPos": {
        "h": 6,
        "w": 5,
        "x": 5,
        "y": 0
      },
      "id": 4,
      "interval": null,
      "links": [],
      "mappingType": 1,
      "mappingTypes": [
        {
          "name": "value to text",
          "value": 1
        },
        {
          "name": "range to text",
          "value": 2
        }
      ],
      "maxDataPoints": 100,
      "minSpan": 2,
      "nullPointMode": "connected",
      "nullText": null,
      "postfix": "",
      "postfixFontSize": "50%",
      "prefix": "",
      "prefixFontSize": "50%",
      "rangeMaps": [
        {
          "from": "null",
          "text": "N/A",
          "to": "null"
        }
      ],
      "repeatDirection": "h",
      "sparkline": {
        "fillColor": "rgba(31, 118, 189, 0.18)",
        "full": false,
        "lineColor": "rgb(31, 120, 193)",
        "show": true
      },
      "tableColumn": "__name__",
      "targets": [
        {
          "expr": "sort_desc( sum ( rate(pgbouncer_stats_queries_total{database=~\"$db\",hostname=~\"$hostname\"}[1m]) ) )",
          "format": "time_series",
          "intervalFactor": 1,
          "refId": "A"
        }
      ],
      "thresholds": "200000,280000,300000",
      "title": "Stats queries total $db",
      "transparent": true,
      "type": "singlestat",
      "valueFontSize": "80%",
      "valueMaps": [
        {
          "op": "=",
          "text": "N/A",
          "value": "null"
        }
      ],
      "valueName": "current"
    },
    {
      "aliasColors": {},
      "bars": true,
      "dashLength": 10,
      "dashes": false,
      "datasource": "$datasource",
      "decimals": null,
      "fill": 2,
      "gridPos": {
        "h": 6,
        "w": 6,
        "x": 10,
        "y": 0
      },
      "hideTimeOverride": false,
      "id": 2,
      "legend": {
        "alignAsTable": true,
        "avg": false,
        "current": true,
        "hideEmpty": false,
        "hideZero": false,
        "max": false,
        "min": false,
        "rightSide": true,
        "show": true,
        "total": false,
        "values": true
      },
      "lines": false,
      "linewidth": 2,
      "links": [],
      "nullPointMode": "null",
      "percentage": false,
      "pointradius": 5,
      "points": false,
      "renderer": "flot",
      "seriesOverrides": [],
      "spaceLength": 10,
      "stack": false,
      "steppedLine": false,
      "targets": [
        {
          "expr": "sum by (database,hostname) (pgbouncer_databases_database_pool_size{database=~\"$db\",hostname=~\"$hostname\"})",
          "format": "time_series",
          "intervalFactor": 1,
          "legendFormat": "{{database}},{{hostname}}",
          "refId": "A"
        }
      ],
      "thresholds": [],
      "timeFrom": null,
      "timeShift": null,
      "title": "Database pool size.",
      "tooltip": {
        "shared": false,
        "sort": 0,
        "value_type": "individual"
      },
      "type": "graph",
      "xaxis": {
        "buckets": null,
        "mode": "series",
        "name": null,
        "show": false,
        "values": [
          "current"
        ]
      },
      "yaxes": [
        {
          "format": "short",
          "label": null,
          "logBase": 1,
          "max": null,
          "min": null,
          "show": true
        },
        {
          "format": "short",
          "label": null,
          "logBase": 1,
          "max": null,
          "min": null,
          "show": true
        }
      ],
      "yaxis": {
        "align": false,
        "alignLevel": null
      }
    },
    {
      "aliasColors": {},
      "bars": true,
      "dashLength": 10,
      "dashes": false,
      "datasource": "$datasource",
      "decimals": null,
      "fill": 2,
      "gridPos": {
        "h": 6,
        "w": 6,
        "x": 16,
        "y": 0
      },
      "hideTimeOverride": false,
      "id": 17,
      "legend": {
        "alignAsTable": true,
        "avg": false,
        "current": true,
        "hideEmpty": false,
        "hideZero": false,
        "max": false,
        "min": false,
        "rightSide": true,
        "show": true,
        "total": false,
        "values": true
      },
      "lines": false,
      "linewidth": 2,
      "links": [],
      "nullPointMode": "null",
      "percentage": false,
      "pointradius": 5,
      "points": false,
      "renderer": "flot",
      "seriesOverrides": [],
      "spaceLength": 10,
      "stack": false,
      "steppedLine": false,
      "targets": [
        {
          "expr": "sum by (database,hostname) (pgbouncer_databases_database_reserve_pool_size{database=~\"$db\",hostname=~\"$hostname\"})",
          "format": "time_series",
          "intervalFactor": 1,
          "legendFormat": "{{database}},{{hostname}}",
          "refId": "A"
        }
      ],
      "thresholds": [],
      "timeFrom": null,
      "timeShift": null,
      "title": "Databases database reserve pool size.",
      "tooltip": {
        "shared": false,
        "sort": 0,
        "value_type": "individual"
      },
      "type": "graph",
      "xaxis": {
        "buckets": null,
        "mode": "series",
        "name": null,
        "show": false,
        "values": [
          "current"
        ]
      },
      "yaxes": [
        {
          "format": "short",
          "label": null,
          "logBase": 1,
          "max": null,
          "min": null,
          "show": true
        },
        {
          "format": "short",
          "label": null,
          "logBase": 1,
          "max": null,
          "min": null,
          "show": true
        }
      ],
      "yaxis": {
        "align": false,
        "alignLevel": null
      }
    },
    {
      "aliasColors": {},
      "bars": false,
      "dashLength": 10,
      "dashes": false,
      "datasource": "$datasource",
      "decimals": null,
      "fill": 2,
      "gridPos": {
        "h": 7,
        "w": 24,
        "x": 0,
        "y": 6
      },
      "id": 16,
      "legend": {
        "avg": true,
        "current": false,
        "hideEmpty": true,
        "hideZero": true,
        "max": false,
        "min": false,
        "show": true,
        "total": false,
        "values": true
      },
      "lines": true,
      "linewidth": 2,
      "links": [],
      "nullPointMode": "null",
      "percentage": false,
      "pointradius": 5,
      "points": true,
      "renderer": "flot",
      "seriesOverrides": [],
      "spaceLength": 10,
      "stack": false,
      "steppedLine": false,
      "targets": [
        {
          "expr": "sort_desc( sum by (database) ( rate(pgbouncer_stats_queries_duration_microseconds{database=~\"$db\",hostname=~\"$hostname\"}[1m]) ) )",
          "format": "time_series",
          "intervalFactor": 1,
          "legendFormat": "{{database}}",
          "refId": "A"
        }
      ],
      "thresholds": [],
      "timeFrom": null,
      "timeShift": null,
      "title": "Total Query Time",
      "tooltip": {
        "shared": true,
        "sort": 2,
        "value_type": "individual"
      },
      "type": "graph",
      "xaxis": {
        "buckets": null,
        "mode": "time",
        "name": null,
        "show": true,
        "values": []
      },
      "yaxes": [
        {
          "format": "µs",
          "label": null,
          "logBase": 1,
          "max": null,
          "min": null,
          "show": true
        },
        {
          "format": "short",
          "label": null,
          "logBase": 1,
          "max": null,
          "min": null,
          "show": false
        }
      ],
      "yaxis": {
        "align": false,
        "alignLevel": null
      }
    },
    {
      "aliasColors": {
        "Stats queries duration microseconds": "#5195ce"
      },
      "bars": true,
      "dashLength": 10,
      "dashes": false,
      "datasource": "$datasource",
      "fill": 0,
      "gridPos": {
        "h": 10,
        "w": 12,
        "x": 0,
        "y": 13
      },
      "id": 12,
      "legend": {
        "alignAsTable": true,
        "avg": true,
        "current": true,
        "hideEmpty": true,
        "hideZero": true,
        "max": true,
        "min": true,
        "show": true,
        "total": false,
        "values": true
      },
      "lines": false,
      "linewidth": 1,
      "links": [],
      "nullPointMode": "null",
      "percentage": false,
      "pointradius": 5,
      "points": false,
      "renderer": "flot",
      "seriesOverrides": [
        {
          "alias": ""
        }
      ],
      "spaceLength": 10,
      "stack": false,
      "steppedLine": false,
      "targets": [
        {
          "expr": "sort_desc( sum by (database, hostname) ( rate(pgbouncer_stats_queries_duration_microseconds{database=~\"$db\",hostname=~\"$hostname\"}[1m]) ) )",
          "format": "time_series",
          "hide": false,
          "intervalFactor": 1,
          "legendFormat": "{{ database }}, {{ hostname }}: Stats queries duration microseconds",
          "refId": "B"
        },
        {
          "expr": "sort_desc( sum by (database, hostname) ( rate(pgbouncer_stats_waiting_duration_microseconds{database=~\"$db\",hostname=~\"$hostname\"}[1m]) ) ) ",
          "format": "time_series",
          "intervalFactor": 1,
          "legendFormat": "{{ database }}, {{hostname}}: Stats waiting duration microseconds",
          "refId": "C"
        }
      ],
      "thresholds": [],
      "timeFrom": null,
      "timeShift": null,
      "title": "Stats queries $db",
      "tooltip": {
        "shared": true,
        "sort": 0,
        "value_type": "individual"
      },
      "type": "graph",
      "xaxis": {
        "buckets": null,
        "mode": "time",
        "name": null,
        "show": true,
        "values": []
      },
      "yaxes": [
        {
          "format": "short",
          "label": null,
          "logBase": 1,
          "max": null,
          "min": null,
          "show": true
        },
        {
          "format": "short",
          "label": null,
          "logBase": 1,
          "max": null,
          "min": null,
          "show": true
        }
      ]
    },
    {
      "aliasColors": {
        "Stats transactions duration microseconds": "#cca300",
        "Stats transactions total": "#962d82"
      },
      "bars": false,
      "dashLength": 10,
      "dashes": false,
      "datasource": "$datasource",
      "decimals": 2,
      "fill": 2,
      "gridPos": {
        "h": 10,
        "w": 12,
        "x": 12,
        "y": 13
      },
      "id": 13,
      "legend": {
        "alignAsTable": true,
        "avg": true,
        "current": true,
        "hideEmpty": true,
        "hideZero": true,
        "max": true,
        "min": true,
        "show": true,
        "total": false,
        "values": true
      },
      "lines": true,
      "linewidth": 2,
      "links": [],
      "nullPointMode": "null",
      "percentage": true,
      "pointradius": 5,
      "points": false,
      "renderer": "flot",
      "seriesOverrides": [],
      "spaceLength": 10,
      "stack": false,
      "steppedLine": false,
      "targets": [
        {
          "expr": "sort_desc( sum by (database, hostname) ( rate(pgbouncer_stats_transactions_duration_microseconds{database=~\"$db\",hostname=~\"$hostname\"}[1m]) ) )  ",
          "format": "time_series",
          "intervalFactor": 1,
          "legendFormat": "{{ database }}, {{ hostname }}: Stats transactions duration microseconds",
          "refId": "D"
        },
        {
          "expr": "sort_desc( sum by (database, hostname) ( rate(pgbouncer_stats_transactions_total{database=~\"$db\",hostname=~\"$hostname\"}[1m]) ) )",
          "format": "time_series",
          "intervalFactor": 1,
          "legendFormat": "{{ database }}, {{ hostname }}: Stats transactions total",
          "refId": "A"
        }
      ],
      "thresholds": [],
      "timeFrom": null,
      "timeShift": null,
      "title": "Transactions stats $db",
      "tooltip": {
        "shared": true,
        "sort": 0,
        "value_type": "individual"
      },
      "type": "graph",
      "xaxis": {
        "buckets": null,
        "mode": "time",
        "name": null,
        "show": true,
        "values": []
      },
      "yaxes": [
        {
          "format": "short",
          "label": null,
          "logBase": 1,
          "max": null,
          "min": null,
          "show": true
        },
        {
          "format": "short",
          "label": null,
          "logBase": 1,
          "max": null,
          "min": null,
          "show": false
        }
      ]
    },
    {
      "aliasColors": {
        "Client active connections": "#b7dbab"
      },
      "bars": false,
      "dashLength": 10,
      "dashes": false,
      "datasource": "$datasource",
      "fill": 0,
      "gridPos": {
        "h": 10,
        "w": 12,
        "x": 0,
        "y": 23
      },
      "id": 15,
      "legend": {
        "alignAsTable": true,
        "avg": true,
        "current": true,
        "hideEmpty": true,
        "hideZero": true,
        "max": true,
        "min": true,
        "show": true,
        "total": false,
        "values": true
      },
      "lines": true,
      "linewidth": 2,
      "links": [],
      "nullPointMode": "null",
      "percentage": false,
      "pointradius": 5,
      "points": false,
      "renderer": "flot",
      "seriesOverrides": [],
      "spaceLength": 10,
      "stack": false,
      "steppedLine": false,
      "targets": [
        {
          "expr": "pgbouncer_pools_client_active_connections{database=~\"$db\", hostname=~\"$hostname\"}",
          "format": "time_series",
          "instant": false,
          "intervalFactor": 1,
          "legendFormat": "{{ database }},{{hostname}}: Client active connections ",
          "refId": "A"
        },
        {
          "expr": "pgbouncer_pools_client_waiting_connections{database=~\"$db\", hostname=~\"$hostname\"}",
          "format": "time_series",
          "intervalFactor": 1,
          "legendFormat": "{{ database }},{{hostname}}: Client waiting connections",
          "refId": "C"
        },
        {
          "expr": "pgbouncer_pools_server_active_connections{database=~\"$db\", hostname=~\"$hostname\"}",
          "format": "time_series",
          "intervalFactor": 1,
          "legendFormat": "{{ database }},{{hostname}}: Server active connections",
          "refId": "B"
        },
        {
          "expr": "pgbouncer_pools_server_idle_connections{database=~\"$db\", hostname=~\"$hostname\"}",
          "format": "time_series",
          "intervalFactor": 1,
          "legendFormat": "{{ database }},{{hostname}}: Server idle connections",
          "refId": "D"
        },
        {
          "expr": "pgbouncer_pools_server_used_connections{database=~\"$db\", hostname=~\"$hostname\"}",
          "format": "time_series",
          "intervalFactor": 1,
          "legendFormat": "{{ database }},{{hostname}}: Server used connections",
          "refId": "E"
        },
        {
          "expr": "pgbouncer_pools_server_testing_connections{database=~\"$db\", hostname=~\"$hostname\"}",
          "format": "time_series",
          "intervalFactor": 1,
          "legendFormat": "{{ database }},{{hostname}}: Server testing connections",
          "refId": "F"
        },
        {
          "expr": "pgbouncer_pools_server_login_connections{database=~\"$db\", hostname=~\"$hostname\"}",
          "format": "time_series",
          "intervalFactor": 1,
          "legendFormat": "{{ database }},{{hostname}}: Server login connections",
          "refId": "G"
        },
        {
          "expr": "pgbouncer_databases_database_current_connections{database=~\"$db\", hostname=~\"$hostname\"}",
          "format": "time_series",
          "intervalFactor": 1,
          "legendFormat": "{{ database }},{{hostname}}: Database current connections",
          "refId": "H"
        }
      ],
      "thresholds": [],
      "timeFrom": null,
      "timeShift": null,
      "title": "Pgbouncer pools connections",
      "tooltip": {
        "shared": true,
        "sort": 0,
        "value_type": "individual"
      },
      "type": "graph",
      "xaxis": {
        "buckets": null,
        "mode": "time",
        "name": null,
        "show": true,
        "values": []
      },
      "yaxes": [
        {
          "format": "short",
          "label": null,
          "logBase": 1,
          "max": null,
          "min": null,
          "show": true
        },
        {
          "format": "short",
          "label": null,
          "logBase": 1,
          "max": null,
          "min": null,
          "show": true
        }
      ]
    },
    {
      "aliasColors": {
        "Stats received bytes total": "#3333ff",
        "Stats sent bytes total": "#00aa00"
      },
      "bars": false,
      "dashLength": 10,
      "dashes": false,
      "datasource": "$datasource",
      "fill": 3,
      "gridPos": {
        "h": 10,
        "w": 12,
        "x": 12,
        "y": 23
      },
      "id": 14,
      "legend": {
        "alignAsTable": true,
        "avg": true,
        "current": true,
        "hideEmpty": true,
        "hideZero": true,
        "max": true,
        "min": true,
        "show": true,
        "total": false,
        "values": true
      },
      "lines": true,
      "linewidth": 2,
      "links": [],
      "nullPointMode": "null",
      "percentage": false,
      "pointradius": 5,
      "points": false,
      "renderer": "flot",
      "seriesOverrides": [
        {
          "alias": "/.*sent.*/",
          "transform": "negative-Y"
        }
      ],
      "spaceLength": 10,
      "stack": false,
      "steppedLine": false,
      "targets": [
        {
          "expr": "sort_desc( sum by (database,hostname) ( rate(pgbouncer_stats_received_bytes_total{database=~\"$db\",hostname=~\"$hostname\"}[1m])*8 ) )",
          "format": "time_series",
          "hide": false,
          "intervalFactor": 1,
          "legendFormat": "{{ database }}, {{ hostname }}: Stats received bytes total",
          "refId": "B"
        },
        {
          "expr": "sort_desc( sum by (database,hostname) ( rate(pgbouncer_stats_sent_bytes_total{database=~\"$db\",hostname=~\"$hostname\"}[1m])*8 ) )",
          "format": "time_series",
          "intervalFactor": 1,
          "legendFormat": "{{ database }}, {{ hostname }}: Stats sent bytes total",
          "refId": "C"
        }
      ],
      "thresholds": [],
      "timeFrom": null,
      "timeShift": null,
      "title": "Total of incoming / outgoing bytes $db",
      "tooltip": {
        "shared": true,
        "sort": 0,
        "value_type": "individual"
      },
      "type": "graph",
      "xaxis": {
        "buckets": null,
        "mode": "time",
        "name": null,
        "show": true,
        "values": []
      },
      "yaxes": [
        {
          "format": "bytes",
          "label": null,
          "logBase": 1,
          "max": null,
          "min": null,
          "show": true
        },
        {
          "format": "short",
          "label": null,
          "logBase": 1,
          "max": null,
          "min": null,
          "show": false
        }
      ]
    }
  ],
  "schemaVersion": 16,
  "style": "dark",
  "tags": [],
  "templating": {
    "list": [
      {
        "allValue": null,
        "current": {},
        "datasource": "${DS_PROMETHEUS_PGbouncer}",
        "hide": 2,
        "includeAll": true,
        "label": "Host",
        "multi": true,
        "name": "host",
        "options": [],
        "query": "label_values(pgbouncer_up, instance)",
        "refresh": 1,
        "regex": "/([^:]+):.*/",
        "sort": 1,
        "tagValuesQuery": "",
        "tags": [],
        "tagsQuery": "",
        "type": "query",
        "useTags": false
      },
      {
        "allValue": null,
        "current": {},
        "datasource": "${DS_PROMETHEUS_PGbouncer}",
        "hide": 2,
        "includeAll": true,
        "label": null,
        "multi": false,
        "name": "port",
        "options": [],
        "query": "label_values(pgbouncer_up, instance)",
        "refresh": 1,
        "regex": "/[^:]+:(.*)/",
        "sort": 0,
        "tagValuesQuery": "",
        "tags": [],
        "tagsQuery": "",
        "type": "query",
        "useTags": false
      },
      {
        "allValue": null,
        "current": {},
        "datasource": "${DS_PROMETHEUS_PGbouncer}",
        "hide": 0,
        "includeAll": true,
        "label": "Db",
        "multi": true,
        "name": "db",
        "options": [],
        "query": "label_values(pgbouncer_databases_database_current_connections,database)",
        "refresh": 1,
        "regex": "",
        "sort": 1,
        "tagValuesQuery": "",
        "tags": [],
        "tagsQuery": "",
        "type": "query",
        "useTags": false
      },
      {
        "allValue": null,
        "current": {},
        "datasource": "${DS_PROMETHEUS_PGbouncer}",
        "hide": 0,
        "includeAll": true,
        "label": "Hostname",
        "multi": true,
        "name": "hostname",
        "options": [],
        "query": "label_values(pgbouncer_up, hostname)",
        "refresh": 1,
        "regex": "",
        "sort": 1,
        "tagValuesQuery": "",
        "tags": [],
        "tagsQuery": "",
        "type": "query",
        "useTags": false
      },
      {
        "current": {
          "selected": true,
          "text": "Prometheus PGbouncer",
          "value": "Prometheus PGbouncer"
        },
        "hide": 0,
        "label": "Datasource",
        "name": "datasource",
        "options": [],
        "query": "prometheus",
        "refresh": 1,
        "regex": "",
        "type": "datasource"
      }
    ]
  },
  "time": {
    "from": "now-1h",
    "to": "now"
  },
  "timepicker": {
    "refresh_intervals": [
      "5s",
      "10s",
      "30s",
      "1m",
      "5m",
      "15m",
      "30m",
      "1h",
      "2h",
      "1d"
    ],
    "time_options": [
      "5m",
      "15m",
      "1h",
      "6h",
      "12h",
      "24h",
      "2d",
      "7d",
      "30d"
    ]
  },
  "timezone": "browser",
  "title": "PostgreSQL PGbouncer",
  "uid": "ZEGmB3lik",
  "version": 123
}